{"chunk_definitions":[{"row":9,"row_count":1,"visible":true,"expansion_state":0,"options":{"engine":"r","label":"setup","include":false},"document_id":"73E8BD89","chunk_id":"csetup_chunk","chunk_label":"setup"},{"row":17,"row_count":1,"visible":true,"expansion_state":0,"options":{"engine":"r","label":"call in libraries and clean data","include":false},"document_id":"73E8BD89","chunk_id":"cfups8qisbnog","chunk_label":"call in libraries and clean data"}],"doc_write_time":1698257575,"working_dir":null,"default_chunk_options":{"echo":true}}